meth/__init__.py
meth/builtins.py
meth/error.py
meth/interpreter.py
meth/lexer.py
meth/nodes.py
meth/parser.py
meth/token.py
meth/utils.py
meth/functions/__init__.py
meth/functions/simplify.py
meth/functions/stringify.py
meth-1.2.1.dist-info/METADATA
meth-1.2.1.dist-info/WHEEL
meth-1.2.1.dist-info/licenses/LICENSE
meth-1.2.1.dist-info/RECORD
