Metadata-Version: 2.1
Name: meth
Version: 1.2.1
Summary: A mathematical expression parser and evaluator.
Project-URL: Homepage, https://github.com/sertdfyguhi/meth
Project-URL: Bug Tracker, https://github.com/sertdfyguhi/meth/issues
Author: sertdfyguhi
License-File: LICENSE
Keywords: evaluator,math,math evaluator,math parser,mathematical,parser,parsing
Classifier: Development Status :: 4 - Beta
Classifier: License :: OSI Approved :: GNU General Public License v3 (GPLv3)
Classifier: Operating System :: OS Independent
Classifier: Programming Language :: Python
Classifier: Programming Language :: Python :: 3
Classifier: Programming Language :: Python :: 3.11
Classifier: Topic :: Scientific/Engineering :: Mathematics
Requires-Python: >=3.0
